spongebox/__init__.py
spongebox/encoding.py
spongebox/io.py
spongebox/iobox.py
spongebox/loanbox.py
spongebox/mediabox.py
spongebox/plotbox.py
spongebox/rebox.py
spongebox/reg.py
spongebox/structbox.py
spongebox/time.py
spongebox/timebox.py
spongebox/financebox/__init__.py
spongebox/financebox/loanbox.py
spongebox/financebox/monetarybox.py
spongeboxtest/__init__.py
spongeboxtest/financeboxtest/__init__.py
spongeboxtest/financeboxtest/gen_repay_plan_test.py
spongeboxtest/ioboxtest/__init__.py
spongeboxtest/ioboxtest/list_dir_test.py
spongeboxtest/ioboxtest/mkdir_test.py
spongeboxtest/ioboxtest/read_overwrite_test.py
spongeboxtest/ioboxtest/to_excel_test.py
spongeboxtest/ioboxtest/zip_dir_test.py
spongeboxtest/loanboxtest/__init__.py
spongeboxtest/loanboxtest/profit_test.py
spongeboxtest/loanboxtest/repayplan_test.py
spongeboxtest/mediaboxtest/Tailortest.py
spongeboxtest/mediaboxtest/__init__.py
spongeboxtest/plotboxtest/__init__.py
spongeboxtest/plotboxtest/grid_plot_test.py
spongeboxtest/reboxtest/__init__.py
spongeboxtest/reboxtest/filter_list_test.py
spongeboxtest/structboxtest/__init__.py
spongeboxtest/structboxtest/flatten_list_test.py
spongeboxtest/timeboxtest/__init__.py
spongeboxtest/timeboxtest/chinesecalendar_test.py
spongeboxtest/timeboxtest/format_match_test.py
spongeboxtest/timeboxtest/strftime_test.py
spongebox-0.3.8.dist-info/LICENSE
spongebox-0.3.8.dist-info/METADATA
spongebox-0.3.8.dist-info/WHEEL
spongebox-0.3.8.dist-info/top_level.txt
spongebox-0.3.8.dist-info/RECORD
