Metadata-Version: 2.1
Name: spongebox
Version: 0.3.8
Summary: A high-level wrapped tool-chest with frequently-used functionalities
Home-page: https://github.com/23spongebob/spongebox
Author: spongebob
Author-email: author@example.com
Classifier: Programming Language :: Python :: 3
Classifier: License :: OSI Approved :: MIT License
Classifier: Operating System :: OS Independent
Requires-Python: >=3.11
License-File: LICENSE
